{"inkVersion":21,"root":[[{"->":"start"},["done",{"#n":"g-0"}],null],"done",{"start":[["^现场已经暴露出消防、资料、进度等多条隐患线索。项目部需要一份正式风险登记台账。","\n","^监理建议按「发生概率 × 影响程度」分级，总包希望先列清单再分级。甲方代表要求本周内能看到初稿。","\n","^你决定怎么建立这份台账。","\n","ev","str","^稳妥推进：组织专题会建立分级台账","/str","/ev",{"*":".^.c-0","flg":20},"ev","str","^快速推进：先汇总清单再补充分级","/str","/ev",{"*":".^.c-1","flg":20},"ev","str","^暂缓协调：暂时口头同步","/str","/ev",{"*":".^.c-2","flg":20},{"c-0":["\n",{"->":"steady_push"},{"#f":5}],"c-1":["\n",{"->":"fast_push"},{"#f":5}],"c-2":["\n",{"->":"delay_coord"},{"#f":5}]}],null],"steady_push":["^你组织专题会，汇总各部门风险点并建立分级台账，明确责任人与跟踪频率。台账质量高，会议占用半天。","\n","end",null],"fast_push":["^你先快速汇总各部门风险点形成清单，分级规则后续补充。台账本周内可见，但部分条目仍需核实。","\n","end",null],"delay_coord":["^你选择先口头同步主要风险，书面台账下周再整理。当前消耗少，但缺少正式留痕。","\n","end",null]}],"listDefs":{}}